xym/__init__.py
xym/xym.py
xym-0.4.2.data/scripts/xym
xym-0.4.2.dist-info/DESCRIPTION.rst
xym-0.4.2.dist-info/METADATA
xym-0.4.2.dist-info/RECORD
xym-0.4.2.dist-info/WHEEL
xym-0.4.2.dist-info/metadata.json
xym-0.4.2.dist-info/top_level.txt
