Metadata-Version: 2.0
Name: xym
Version: 0.4.2
Summary: A tool to fetch and extract YANG modules from IETF RFCs and Drafts
Home-page: https://github.com/xym-tool/xym
Author: Jan Medved
Author-email: jmedved@cisco.com
License: New-style BSD
Keywords: yang,extraction
Platform: UNKNOWN
Requires-Dist: requests (>=2.6)
